rio_bootstrap/__init__.py
rio_bootstrap/bootstrap.tar.xz
rio_bootstrap-0.1.0.dist-info/METADATA
rio_bootstrap-0.1.0.dist-info/WHEEL
rio_bootstrap-0.1.0.dist-info/licenses/LICENSE.txt
rio_bootstrap-0.1.0.dist-info/RECORD
