Metadata-Version: 2.3
Name: rio-bootstrap
Version: 0.1.0
Summary: Brings Bootstrap icons to Rio
Project-URL: homepage, https://rio.dev
Project-URL: repository, https://github.com/rio-labs/rio-bootstrap
Project-URL: documentation, https://rio.dev/docs/api/Icon
Author-email: Jakob Pinterits <jakob.pinterits@gmail.com>
License: Copyright (c) 2025 Jakob Pinterits
Keywords: app,framework,functional,local-app,modern,rio,user-interface,web,web-app,web-development,web-framework
Classifier: Development Status :: 4 - Beta
Classifier: Intended Audience :: Developers
Classifier: Intended Audience :: Financial and Insurance Industry
Classifier: Intended Audience :: Information Technology
Classifier: License :: OSI Approved :: MIT License
Classifier: Operating System :: OS Independent
Classifier: Programming Language :: Python :: 3.10
Classifier: Programming Language :: Python :: 3.11
Classifier: Programming Language :: Python :: 3.12
Classifier: Programming Language :: Python :: 3.13
Classifier: Topic :: Internet :: WWW/HTTP :: Dynamic Content
Classifier: Topic :: Internet :: WWW/HTTP :: WSGI :: Application
Classifier: Topic :: Software Development :: Libraries :: Python Modules
Requires-Python: >=3.10
Requires-Dist: rio-ui<1.0,>=0.10.9
